graphene_pandas/__init__.py
graphene_pandas/dataframe_types.py
graphene_pandas/utils.py
graphene_pandas/tests/__init__.py
graphene_pandas/tests/test_graphene_pandas.py
graphene_pandas-0.1.1.dist-info/LICENSE.md
graphene_pandas-0.1.1.dist-info/METADATA
graphene_pandas-0.1.1.dist-info/WHEEL
graphene_pandas-0.1.1.dist-info/top_level.txt
graphene_pandas-0.1.1.dist-info/RECORD
