Metadata-Version: 2.1
Name: graphene-pandas
Version: 0.1.1
Summary: Graphene Pandas integration
Home-page: https://github.com/ig-ksv/graphene-pandas
Author: Igor Kozintsev
Author-email: ig.kozintsev@gmail.com
License: MIT
Keywords: api graphql protocol graphene,pandas
Platform: UNKNOWN
Classifier: Development Status :: 1 - Planning
Classifier: Intended Audience :: Developers
Classifier: Topic :: Software Development :: Libraries
Classifier: Programming Language :: Python :: 3.7
Requires-Dist: graphene (==2.1.8)
Requires-Dist: numpy (==1.19.5)
Requires-Dist: pandas (==1.2.0)
Provides-Extra: dev
Requires-Dist: tox (==3.7.0) ; extra == 'dev'
Requires-Dist: coveralls (==1.10.0) ; extra == 'dev'
Provides-Extra: test
Requires-Dist: pytest (==6.2.1) ; extra == 'test'
Requires-Dist: mock (==2.0.0) ; extra == 'test'
Requires-Dist: pytest-cov (==2.6.1) ; extra == 'test'
Requires-Dist: pytest-benchmark (==3.2.1) ; extra == 'test'
